{
 	"bos": {
 		"Players" : [
		{
			"PlayerName" : "Fernando Abad",
			"Position" :  "P"
		},

		{
			"PlayerName" : "Matt Barnes",
			"Position" :  "P"
		},

		{
			"PlayerName" : "Blaine Boyer",
			"Position" :  "P"
		},

		{
			"PlayerName" : "Roenis Elias",
			"Position" :  "P"
		},

		{
			"PlayerName" : "Doug Fister",
			"Position" :  "P"
		},

		{
			"PlayerName" : "Heath Hembree",
			"Position" :  "P"
		},

		{
			"PlayerName" : "Joe Kelly",
			"Position" :  "P"
		},

		{
			"PlayerName" : "Craig Kimbrel",
			"Position" :  "P"
		},

		{
			"PlayerName" : "Austin Maddox",
			"Position" :  "P"
		},

		{
			"PlayerName" : "Drew Pomeranz",
			"Position" :  "P"
		},

		{
			"PlayerName" : "Rick Porcello",
			"Position" :  "P"
		},

		{
			"PlayerName" : "Addison Reed",
			"Position" :  "P"
		},

		{
			"PlayerName" : "Eduardo Rodriguez",
			"Position" :  "P"
		},

		{
			"PlayerName" : "Chris Sale",
			"Position" :  "P"
		},

		{
			"PlayerName" : "Robby Scott",
			"Position" :  "P"
		},

		{
			"PlayerName" : "Carson Smith",
			"Position" :  "P"
		},

		{
			"PlayerName" : "Hector Velazquez",
			"Position" :  "P"
		},

		{
			"PlayerName" : "Brandon Workman",
			"Position" :  "P"
		},

		{
			"PlayerName" : "Sandy Leon",
			"Position" :  "C"
		},

		{
			"PlayerName" : "Blake Swihart",
			"Position" :  "C"
		},

		{
			"PlayerName" : "Christian Vazquez",
			"Position" :  "C"
		},

		{
			"PlayerName" : "Xander Bogaerts",
			"Position" :  "IF"
		},

		{
			"PlayerName" : "Rafael Devers",
			"Position" :  "IF"
		},

		{
			"PlayerName" : "Brock Holt",
			"Position" :  "IF"
		},

		{
			"PlayerName" : "Deven Marrero",
			"Position" :  "IF"
		},

		{
			"PlayerName" : "Mitch Moreland",
			"Position" :  "IF"
		},

		{
			"PlayerName" : "Eduardo Nunez",
			"Position" :  "IF"
		},

		{
			"PlayerName" : "Dustin Pedroia",
			"Position" :  "IF"
		},

		{
			"PlayerName" : "Sam Travis",
			"Position" :  "IF"
		},

		{
			"PlayerName" : "Andrew Benintendi",
			"Position" :  "OF"
		},

		{
			"PlayerName" : "Mookie Betts",
			"Position" :  "OF"
		},

		{
			"PlayerName" : "Jackie Bradley Jr.",
			"Position" :  "OF"
		},

		{
			"PlayerName" : "Rajai Davis",
			"Position" :  "OF"
		},

		{
			"PlayerName" : "Tzu-Wei Lin",
			"Position" :  "OF"
		},

		{
			"PlayerName" : "Chris Young",
			"Position" :  "OF"
		},

		{
			"PlayerName" : "Hanley Ramirez",
			"Position" :  "DH"
		}
		]
	},
 	"nyy": {
 		"Players" : [
		{
			"PlayerName" : "Dellin Betances",
			"Position" :  "P"
		},

		{
			"PlayerName" : "Aroldis Chapman",
			"Position" :  "P"
		},

		{
			"PlayerName" : "Giovanny Gallegos",
			"Position" :  "P"
		},

		{
			"PlayerName" : "Jaime Garcia",
			"Position" :  "P"
		},

		{
			"PlayerName" : "Sonny Gray",
			"Position" :  "P"
		},

		{
			"PlayerName" : "Chad Green",
			"Position" :  "P"
		},

		{
			"PlayerName" : "Ben Heller",
			"Position" :  "P"
		},

		{
			"PlayerName" : "Tommy Kahnle",
			"Position" :  "P"
		},

		{
			"PlayerName" : "Bryan Mitchell",
			"Position" :  "P"
		},

		{
			"PlayerName" : "Jordan Montgomery",
			"Position" :  "P"
		},

		{
			"PlayerName" : "David Robertson",
			"Position" :  "P"
		},

		{
			"PlayerName" : "CC Sabathia",
			"Position" :  "P"
		},

		{
			"PlayerName" : "Luis Severino",
			"Position" :  "P"
		},

		{
			"PlayerName" : "Chasen Shreve",
			"Position" :  "P"
		},

		{
			"PlayerName" : "Caleb Smith",
			"Position" :  "P"
		},

		{
			"PlayerName" : "Masahiro Tanaka",
			"Position" :  "P"
		},

		{
			"PlayerName" : "Erik Kratz",
			"Position" :  "C"
		},

		{
			"PlayerName" : "Austin Romine",
			"Position" :  "C"
		},

		{
			"PlayerName" : "Gary Sanchez",
			"Position" :  "C"
		},

		{
			"PlayerName" : "Tyler Austin",
			"Position" :  "IF"
		},

		{
			"PlayerName" : "Greg Bird",
			"Position" :  "IF"
		},

		{
			"PlayerName" : "Starlin Castro",
			"Position" :  "IF"
		},

		{
			"PlayerName" : "Todd Frazier",
			"Position" :  "IF"
		},

		{
			"PlayerName" : "Didi Gregorius",
			"Position" :  "IF"
		},

		{
			"PlayerName" : "Chase Headley",
			"Position" :  "IF"
		},

		{
			"PlayerName" : "Ronald Torreyes",
			"Position" :  "IF"
		},

		{
			"PlayerName" : "Tyler Wade",
			"Position" :  "IF"
		},

		{
			"PlayerName" : "Jacoby Ellsbury",
			"Position" :  "OF"
		},

		{
			"PlayerName" : "Brett Gardner",
			"Position" :  "OF"
		},

		{
			"PlayerName" : "Aaron Judge",
			"Position" :  "OF"
		},

		{
			"PlayerName" : "Matt Holliday",
			"Position" :  "DH"
		}
		]
	},
 	"nym": {
 		"Players" : [
		{
			"PlayerName" : "Jerry Blevins",
			"Position" :  "P"
		},

		{
			"PlayerName" : "Chasen Bradford",
			"Position" :  "P"
		},

		{
			"PlayerName" : "Jamie Callahan",
			"Position" :  "P"
		},

		{
			"PlayerName" : "Jacob deGrom",
			"Position" :  "P"
		},

		{
			"PlayerName" : "Jeurys Familia",
			"Position" :  "P"
		},

		{
			"PlayerName" : "Chris Flexen",
			"Position" :  "P"
		},

		{
			"PlayerName" : "Erik Goeddel",
			"Position" :  "P"
		},

		{
			"PlayerName" : "Robert Gsellman",
			"Position" :  "P"
		},

		{
			"PlayerName" : "Matt Harvey",
			"Position" :  "P"
		},

		{
			"PlayerName" : "Seth Lugo",
			"Position" :  "P"
		},

		{
			"PlayerName" : "Kevin McGowan",
			"Position" :  "P"
		},

		{
			"PlayerName" : "Tommy Milone",
			"Position" :  "P"
		},

		{
			"PlayerName" : "Rafael Montero",
			"Position" :  "P"
		},

		{
			"PlayerName" : "AJ Ramos",
			"Position" :  "P"
		},

		{
			"PlayerName" : "Jacob Rhame",
			"Position" :  "P"
		},

		{
			"PlayerName" : "Hansel Robles",
			"Position" :  "P"
		},

		{
			"PlayerName" : "Paul Sewald",
			"Position" :  "P"
		},

		{
			"PlayerName" : "Josh Smoker",
			"Position" :  "P"
		},

		{
			"PlayerName" : "Travis dArnaud",
			"Position" :  "C"
		},

		{
			"PlayerName" : "Kevin Plawecki",
			"Position" :  "C"
		},

		{
			"PlayerName" : "Asdrubal Cabrera",
			"Position" :  "IF"
		},

		{
			"PlayerName" : "Gavin Cecchini",
			"Position" :  "IF"
		},

		{
			"PlayerName" : "Phillip Evans",
			"Position" :  "IF"
		},

		{
			"PlayerName" : "Wilmer Flores",
			"Position" :  "IF"
		},

		{
			"PlayerName" : "Jose Reyes",
			"Position" :  "IF"
		},

		{
			"PlayerName" : "Matt Reynolds",
			"Position" :  "IF"
		},

		{
			"PlayerName" : "Amed Rosario",
			"Position" :  "IF"
		},

		{
			"PlayerName" : "Dominic Smith",
			"Position" :  "IF"
		},

		{
			"PlayerName" : "Norichika Aoki",
			"Position" :  "OF"
		},

		{
			"PlayerName" : "Juan Lagares",
			"Position" :  "OF"
		},

		{
			"PlayerName" : "Brandon Nimmo",
			"Position" :  "OF"
		},

		{
			"PlayerName" : "Travis Taijeron",
			"Position" :  "OF"
		}
		]
	},
 	"laa": {
 		"Players" : [
		{
			"PlayerName" : "Jose Alvarez",
			"Position" :  "P"
		},

		{
			"PlayerName" : "Cam Bedrosian",
			"Position" :  "P"
		},

		{
			"PlayerName" : "Parker Bridwell",
			"Position" :  "P"
		},

		{
			"PlayerName" : "Jesse Chavez",
			"Position" :  "P"
		},

		{
			"PlayerName" : "Deolis Guerra",
			"Position" :  "P"
		},

		{
			"PlayerName" : "Jason Gurka",
			"Position" :  "P"
		},

		{
			"PlayerName" : "Andrew Heaney",
			"Position" :  "P"
		},

		{
			"PlayerName" : "Keynan Middleton",
			"Position" :  "P"
		},

		{
			"PlayerName" : "Ricky Nolasco",
			"Position" :  "P"
		},

		{
			"PlayerName" : "Bud Norris",
			"Position" :  "P"
		},

		{
			"PlayerName" : "Eduardo Paredes",
			"Position" :  "P"
		},

		{
			"PlayerName" : "Blake Parker",
			"Position" :  "P"
		},

		{
			"PlayerName" : "Yusmeiro Petit",
			"Position" :  "P"
		},

		{
			"PlayerName" : "Noe Ramirez",
			"Position" :  "P"
		},

		{
			"PlayerName" : "Garrett Richards",
			"Position" :  "P"
		},

		{
			"PlayerName" : "Fernando Salas",
			"Position" :  "P"
		},

		{
			"PlayerName" : "Troy Scribner",
			"Position" :  "P"
		},

		{
			"PlayerName" : "Tyler Skaggs",
			"Position" :  "P"
		},

		{
			"PlayerName" : "Blake Wood",
			"Position" :  "P"
		},

		{
			"PlayerName" : "Juan Graterol",
			"Position" :  "C"
		},

		{
			"PlayerName" : "Martin Maldonado",
			"Position" :  "C"
		},

		{
			"PlayerName" : "Carlos Perez",
			"Position" :  "C"
		},

		{
			"PlayerName" : "Kaleb Cowart",
			"Position" :  "IF"
		},

		{
			"PlayerName" : "C.J. Cron",
			"Position" :  "IF"
		},

		{
			"PlayerName" : "Nolan Fontana",
			"Position" :  "IF"
		},

		{
			"PlayerName" : "Cliff Pennington",
			"Position" :  "IF"
		},

		{
			"PlayerName" : "Brandon Phillips",
			"Position" :  "IF"
		},

		{
			"PlayerName" : "Andrelton Simmons",
			"Position" :  "IF"
		},

		{
			"PlayerName" : "Luis Valbuena",
			"Position" :  "IF"
		},

		{
			"PlayerName" : "Kole Calhoun",
			"Position" :  "OF"
		},

		{
			"PlayerName" : "Ben Revere",
			"Position" :  "OF"
		},

		{
			"PlayerName" : "Shane Robinson",
			"Position" :  "OF"
		},

		{
			"PlayerName" : "Mike Trout",
			"Position" :  "OF"
		},

		{
			"PlayerName" : "Justin Upton",
			"Position" :  "OF"
		},

		{
			"PlayerName" : "Eric Young Jr.",
			"Position" :  "OF"
		},

		{
			"PlayerName" : "Albert Pujols",
			"Position" :  "DH"
		}
		]
	},
 	"lad": {
 		"Players" : [
		{
			"PlayerName" : "Luis Avilan",
			"Position" :  "P"
		},

		{
			"PlayerName" : "Pedro Baez",
			"Position" :  "P"
		},

		{
			"PlayerName" : "Walker Buehler",
			"Position" :  "P"
		},

		{
			"PlayerName" : "Tony Cingrani",
			"Position" :  "P"
		},

		{
			"PlayerName" : "Yu Darvish",
			"Position" :  "P"
		},

		{
			"PlayerName" : "Josh Fields",
			"Position" :  "P"
		},

		{
			"PlayerName" : "Wilmer Font",
			"Position" :  "P"
		},

		{
			"PlayerName" : "Rich Hill",
			"Position" :  "P"
		},

		{
			"PlayerName" : "Kenley Jansen",
			"Position" :  "P"
		},

		{
			"PlayerName" : "Clayton Kershaw",
			"Position" :  "P"
		},

		{
			"PlayerName" : "Kenta Maeda",
			"Position" :  "P"
		},

		{
			"PlayerName" : "Brandon Morrow",
			"Position" :  "P"
		},

		{
			"PlayerName" : "Edward Paredes",
			"Position" :  "P"
		},

		{
			"PlayerName" : "Josh Ravin",
			"Position" :  "P"
		},

		{
			"PlayerName" : "Hyun-Jin Ryu",
			"Position" :  "P"
		},

		{
			"PlayerName" : "Brock Stewart",
			"Position" :  "P"
		},

		{
			"PlayerName" : "Ross Stripling",
			"Position" :  "P"
		},

		{
			"PlayerName" : "Tony Watson",
			"Position" :  "P"
		},

		{
			"PlayerName" : "Alex Wood",
			"Position" :  "P"
		},

		{
			"PlayerName" : "Austin Barnes",
			"Position" :  "C"
		},

		{
			"PlayerName" : "Yasmani Grandal",
			"Position" :  "C"
		},

		{
			"PlayerName" : "Cody Bellinger",
			"Position" :  "IF"
		},

		{
			"PlayerName" : "Charlie Culberson",
			"Position" :  "IF"
		},

		{
			"PlayerName" : "Kyle Farmer",
			"Position" :  "IF"
		},

		{
			"PlayerName" : "Logan Forsythe",
			"Position" :  "IF"
		},

		{
			"PlayerName" : "Adrian Gonzalez",
			"Position" :  "IF"
		},

		{
			"PlayerName" : "Corey Seager",
			"Position" :  "IF"
		},

		{
			"PlayerName" : "Rob Segedin",
			"Position" :  "IF"
		},

		{
			"PlayerName" : "Justin Turner",
			"Position" :  "IF"
		},

		{
			"PlayerName" : "Chase Utley",
			"Position" :  "IF"
		},

		{
			"PlayerName" : "OKoyea Dickson",
			"Position" :  "OF"
		},

		{
			"PlayerName" : "Andre Ethier",
			"Position" :  "OF"
		},

		{
			"PlayerName" : "Curtis Granderson",
			"Position" :  "OF"
		},

		{
			"PlayerName" : "Enrique Hernandez",
			"Position" :  "OF"
		},

		{
			"PlayerName" : "Joc Pederson",
			"Position" :  "OF"
		},

		{
			"PlayerName" : "Yasiel Puig",
			"Position" :  "OF"
		},

		{
			"PlayerName" : "Chris Taylor",
			"Position" :  "OF"
		},

		{
			"PlayerName" : "Trayce Thompson",
			"Position" :  "OF"
		},

		{
			"PlayerName" : "Alex Verdugo",
			"Position" :  "OF"
		}
		]
	},
 	"sf": {
 		"Players" : [
		{
			"PlayerName" : "Ty Blach",
			"Position" :  "P"
		},

		{
			"PlayerName" : "Madison Bumgarner",
			"Position" :  "P"
		},

		{
			"PlayerName" : "Matt Cain",
			"Position" :  "P"
		},

		{
			"PlayerName" : "Kyle Crick",
			"Position" :  "P"
		},

		{
			"PlayerName" : "Johnny Cueto",
			"Position" :  "P"
		},

		{
			"PlayerName" : "Sam Dyson",
			"Position" :  "P"
		},

		{
			"PlayerName" : "Cory Gearrin",
			"Position" :  "P"
		},

		{
			"PlayerName" : "Roberto Gomez",
			"Position" :  "P"
		},

		{
			"PlayerName" : "Derek Law",
			"Position" :  "P"
		},

		{
			"PlayerName" : "Mark Melancon",
			"Position" :  "P"
		},

		{
			"PlayerName" : "Matt Moore",
			"Position" :  "P"
		},

		{
			"PlayerName" : "Reyes Moronta",
			"Position" :  "P"
		},

		{
			"PlayerName" : "Steven Okert",
			"Position" :  "P"
		},

		{
			"PlayerName" : "Josh Osich",
			"Position" :  "P"
		},

		{
			"PlayerName" : "Jeff Samardzija",
			"Position" :  "P"
		},

		{
			"PlayerName" : "Chris Stratton",
			"Position" :  "P"
		},

		{
			"PlayerName" : "Hunter Strickland",
			"Position" :  "P"
		},

		{
			"PlayerName" : "Albert Suarez",
			"Position" :  "P"
		},

		{
			"PlayerName" : "Tim Federowicz",
			"Position" :  "C"
		},

		{
			"PlayerName" : "Nick Hundley",
			"Position" :  "C"
		},

		{
			"PlayerName" : "Buster Posey",
			"Position" :  "C"
		},

		{
			"PlayerName" : "Orlando Calixte",
			"Position" :  "IF"
		},

		{
			"PlayerName" : "Brandon Crawford",
			"Position" :  "IF"
		},

		{
			"PlayerName" : "Ryder Jones",
			"Position" :  "IF"
		},

		{
			"PlayerName" : "Joe Panik",
			"Position" :  "IF"
		},

		{
			"PlayerName" : "Pablo Sandoval",
			"Position" :  "IF"
		},

		{
			"PlayerName" : "Kelby Tomlinson",
			"Position" :  "IF"
		},

		{
			"PlayerName" : "Gorkys Hernandez",
			"Position" :  "OF"
		},

		{
			"PlayerName" : "Jarrett Parker",
			"Position" :  "OF"
		},

		{
			"PlayerName" : "Hunter Pence",
			"Position" :  "OF"
		},

		{
			"PlayerName" : "Austin Slater",
			"Position" :  "OF"
		},

		{
			"PlayerName" : "Denard Span",
			"Position" :  "OF"
		},

		{
			"PlayerName" : "Mac Williamson",
			"Position" :  "OF"
		}
		]
	},
 	"tb": {
 		"Players" : [
		{
			"PlayerName" : "Jose Alvarado",
			"Position" :  "P"
		},

		{
			"PlayerName" : "Matt Andriese",
			"Position" :  "P"
		},

		{
			"PlayerName" : "Chris Archer",
			"Position" :  "P"
		},

		{
			"PlayerName" : "Brad Boxberger",
			"Position" :  "P"
		},

		{
			"PlayerName" : "Steve Cishek",
			"Position" :  "P"
		},

		{
			"PlayerName" : "Alex Cobb",
			"Position" :  "P"
		},

		{
			"PlayerName" : "Alex Colome",
			"Position" :  "P"
		},

		{
			"PlayerName" : "Tommy Hunter",
			"Position" :  "P"
		},

		{
			"PlayerName" : "Dan Jennings",
			"Position" :  "P"
		},

		{
			"PlayerName" : "Andrew Kittredge",
			"Position" :  "P"
		},

		{
			"PlayerName" : "Jake Odorizzi",
			"Position" :  "P"
		},

		{
			"PlayerName" : "Austin Pruitt",
			"Position" :  "P"
		},

		{
			"PlayerName" : "Chaz Roe",
			"Position" :  "P"
		},

		{
			"PlayerName" : "Sergio Romo",
			"Position" :  "P"
		},

		{
			"PlayerName" : "Blake Snell",
			"Position" :  "P"
		},

		{
			"PlayerName" : "Ryne Stanek",
			"Position" :  "P"
		},

		{
			"PlayerName" : "Chase Whitley",
			"Position" :  "P"
		},

		{
			"PlayerName" : "Curt Casali",
			"Position" :  "C"
		},

		{
			"PlayerName" : "Wilson Ramos",
			"Position" :  "C"
		},

		{
			"PlayerName" : "Jesus Sucre",
			"Position" :  "C"
		},

		{
			"PlayerName" : "Lucas Duda",
			"Position" :  "IF"
		},

		{
			"PlayerName" : "Danny Espinosa",
			"Position" :  "IF"
		},

		{
			"PlayerName" : "Adeiny Hechavarria",
			"Position" :  "IF"
		},

		{
			"PlayerName" : "Evan Longoria",
			"Position" :  "IF"
		},

		{
			"PlayerName" : "Brad Miller",
			"Position" :  "IF"
		},

		{
			"PlayerName" : "Logan Morrison",
			"Position" :  "IF"
		},

		{
			"PlayerName" : "Trevor Plouffe",
			"Position" :  "IF"
		},

		{
			"PlayerName" : "Peter Bourjos",
			"Position" :  "OF"
		},

		{
			"PlayerName" : "Corey Dickerson",
			"Position" :  "OF"
		},

		{
			"PlayerName" : "Kevin Kiermaier",
			"Position" :  "OF"
		},

		{
			"PlayerName" : "Cesar Puello",
			"Position" :  "OF"
		},

		{
			"PlayerName" : "Mallex Smith",
			"Position" :  "OF"
		},

		{
			"PlayerName" : "Steven Souza Jr.",
			"Position" :  "OF"
		}
		]
	},
 	"tor": {
 		"Players" : [
		{
			"PlayerName" : "Brett Anderson",
			"Position" :  "P"
		},

		{
			"PlayerName" : "Danny Barnes",
			"Position" :  "P"
		},

		{
			"PlayerName" : "Joe Biagini",
			"Position" :  "P"
		},

		{
			"PlayerName" : "Leonel Campos",
			"Position" :  "P"
		},

		{
			"PlayerName" : "Matt Dermody",
			"Position" :  "P"
		},

		{
			"PlayerName" : "Marco Estrada",
			"Position" :  "P"
		},

		{
			"PlayerName" : "J.A. Happ",
			"Position" :  "P"
		},

		{
			"PlayerName" : "Tom Koehler",
			"Position" :  "P"
		},

		{
			"PlayerName" : "Dominic Leone",
			"Position" :  "P"
		},

		{
			"PlayerName" : "Aaron Loup",
			"Position" :  "P"
		},

		{
			"PlayerName" : "Tim Mayza",
			"Position" :  "P"
		},

		{
			"PlayerName" : "Roberto Osuna",
			"Position" :  "P"
		},

		{
			"PlayerName" : "Carlos Ramirez",
			"Position" :  "P"
		},

		{
			"PlayerName" : "Chris Rowley",
			"Position" :  "P"
		},

		{
			"PlayerName" : "Luis Santos",
			"Position" :  "P"
		},

		{
			"PlayerName" : "Marcus Stroman",
			"Position" :  "P"
		},

		{
			"PlayerName" : "Ryan Tepera",
			"Position" :  "P"
		},

		{
			"PlayerName" : "Raffy Lopez",
			"Position" :  "C"
		},

		{
			"PlayerName" : "Luke Maile",
			"Position" :  "C"
		},

		{
			"PlayerName" : "Miguel Montero",
			"Position" :  "C"
		},

		{
			"PlayerName" : "Darwin Barney",
			"Position" :  "IF"
		},

		{
			"PlayerName" : "Josh Donaldson",
			"Position" :  "IF"
		},

		{
			"PlayerName" : "Ryan Goins",
			"Position" :  "IF"
		},

		{
			"PlayerName" : "Rob Refsnyder",
			"Position" :  "IF"
		},

		{
			"PlayerName" : "Justin Smoak",
			"Position" :  "IF"
		},

		{
			"PlayerName" : "Richard Urena",
			"Position" :  "IF"
		},

		{
			"PlayerName" : "Jose Bautista",
			"Position" :  "OF"
		},

		{
			"PlayerName" : "Ezequiel Carrera",
			"Position" :  "OF"
		},

		{
			"PlayerName" : "Teoscar Hernandez",
			"Position" :  "OF"
		},

		{
			"PlayerName" : "Steve Pearce",
			"Position" :  "OF"
		},

		{
			"PlayerName" : "Kevin Pillar",
			"Position" :  "OF"
		},

		{
			"PlayerName" : "Michael Saunders",
			"Position" :  "OF"
		},

		{
			"PlayerName" : "Kendrys Morales",
			"Position" :  "DH"
		}
		]
	},
 	"bal": {
 		"Players" : [
		{
			"PlayerName" : "Richard Bleier",
			"Position" :  "P"
		},

		{
			"PlayerName" : "Brad Brach",
			"Position" :  "P"
		},

		{
			"PlayerName" : "Zach Britton",
			"Position" :  "P"
		},

		{
			"PlayerName" : "Dylan Bundy",
			"Position" :  "P"
		},

		{
			"PlayerName" : "Miguel Castro",
			"Position" :  "P"
		},

		{
			"PlayerName" : "Kevin Gausman",
			"Position" :  "P"
		},

		{
			"PlayerName" : "Mychal Givens",
			"Position" :  "P"
		},

		{
			"PlayerName" : "Donnie Hart",
			"Position" :  "P"
		},

		{
			"PlayerName" : "Jeremy Hellickson",
			"Position" :  "P"
		},

		{
			"PlayerName" : "Ubaldo Jimenez",
			"Position" :  "P"
		},

		{
			"PlayerName" : "Wade Miley",
			"Position" :  "P"
		},

		{
			"PlayerName" : "Darren ODay",
			"Position" :  "P"
		},

		{
			"PlayerName" : "Richard Rodriguez",
			"Position" :  "P"
		},

		{
			"PlayerName" : "Chris Tillman",
			"Position" :  "P"
		},

		{
			"PlayerName" : "Mike Wright",
			"Position" :  "P"
		},

		{
			"PlayerName" : "Jimmy Yacabonis",
			"Position" :  "P"
		},

		{
			"PlayerName" : "Gabriel Ynoa",
			"Position" :  "P"
		},

		{
			"PlayerName" : "Welington Castillo",
			"Position" :  "C"
		},

		{
			"PlayerName" : "Caleb Joseph",
			"Position" :  "C"
		},

		{
			"PlayerName" : "Chance Sisco",
			"Position" :  "C"
		},

		{
			"PlayerName" : "Pedro Alvarez",
			"Position" :  "IF"
		},

		{
			"PlayerName" : "Tim Beckham",
			"Position" :  "IF"
		},

		{
			"PlayerName" : "Chris Davis",
			"Position" :  "IF"
		},

		{
			"PlayerName" : "Ryan Flaherty",
			"Position" :  "IF"
		},

		{
			"PlayerName" : "J.J. Hardy",
			"Position" :  "IF"
		},

		{
			"PlayerName" : "Manny Machado",
			"Position" :  "IF"
		},

		{
			"PlayerName" : "Jonathan Schoop",
			"Position" :  "IF"
		},

		{
			"PlayerName" : "Austin Hays",
			"Position" :  "OF"
		},

		{
			"PlayerName" : "Adam Jones",
			"Position" :  "OF"
		},

		{
			"PlayerName" : "Trey Mancini",
			"Position" :  "OF"
		},

		{
			"PlayerName" : "Joey Rickard",
			"Position" :  "OF"
		},

		{
			"PlayerName" : "Anthony Santander",
			"Position" :  "OF"
		},

		{
			"PlayerName" : "Seth Smith",
			"Position" :  "OF"
		},

		{
			"PlayerName" : "Mark Trumbo",
			"Position" :  "DH"
		}
		]
	},
 	"stl": {
 		"Players" : [
		{
			"PlayerName" : "Sandy Alcantara",
			"Position" :  "P"
		},

		{
			"PlayerName" : "Matt Bowman",
			"Position" :  "P"
		},

		{
			"PlayerName" : "John Brebbia",
			"Position" :  "P"
		},

		{
			"PlayerName" : "Brett Cecil",
			"Position" :  "P"
		},

		{
			"PlayerName" : "Zach Duke",
			"Position" :  "P"
		},

		{
			"PlayerName" : "Jack Flaherty",
			"Position" :  "P"
		},

		{
			"PlayerName" : "John Gant",
			"Position" :  "P"
		},

		{
			"PlayerName" : "Lance Lynn",
			"Position" :  "P"
		},

		{
			"PlayerName" : "Tyler Lyons",
			"Position" :  "P"
		},

		{
			"PlayerName" : "Carlos Martinez",
			"Position" :  "P"
		},

		{
			"PlayerName" : "Juan Nicasio",
			"Position" :  "P"
		},

		{
			"PlayerName" : "Seung Hwan Oh",
			"Position" :  "P"
		},

		{
			"PlayerName" : "Ryan Sherriff",
			"Position" :  "P"
		},

		{
			"PlayerName" : "Sam Tuivailala",
			"Position" :  "P"
		},

		{
			"PlayerName" : "Michael Wacha",
			"Position" :  "P"
		},

		{
			"PlayerName" : "Luke Weaver",
			"Position" :  "P"
		},

		{
			"PlayerName" : "Carson Kelly",
			"Position" :  "C"
		},

		{
			"PlayerName" : "Yadier Molina",
			"Position" :  "C"
		},

		{
			"PlayerName" : "Alberto Rosario",
			"Position" :  "C"
		},

		{
			"PlayerName" : "Matt Carpenter",
			"Position" :  "IF"
		},

		{
			"PlayerName" : "Paul DeJong",
			"Position" :  "IF"
		},

		{
			"PlayerName" : "Greg Garcia",
			"Position" :  "IF"
		},

		{
			"PlayerName" : "Alex Mejia",
			"Position" :  "IF"
		},

		{
			"PlayerName" : "Breyvic Valera",
			"Position" :  "IF"
		},

		{
			"PlayerName" : "Luke Voit",
			"Position" :  "IF"
		},

		{
			"PlayerName" : "Kolten Wong",
			"Position" :  "IF"
		},

		{
			"PlayerName" : "Harrison Bader",
			"Position" :  "OF"
		},

		{
			"PlayerName" : "Dexter Fowler",
			"Position" :  "OF"
		},

		{
			"PlayerName" : "Randal Grichuk",
			"Position" :  "OF"
		},

		{
			"PlayerName" : "Jose Martinez",
			"Position" :  "OF"
		},

		{
			"PlayerName" : "Tommy Pham",
			"Position" :  "OF"
		},

		{
			"PlayerName" : "Stephen Piscotty",
			"Position" :  "OF"
		}
		]
	},
 	"col": {
 		"Players" : [
		{
			"PlayerName" : "Tyler Anderson",
			"Position" :  "P"
		},

		{
			"PlayerName" : "Chad Bettis",
			"Position" :  "P"
		},

		{
			"PlayerName" : "Shane Carle",
			"Position" :  "P"
		},

		{
			"PlayerName" : "Tyler Chatwood",
			"Position" :  "P"
		},

		{
			"PlayerName" : "Mike Dunn",
			"Position" :  "P"
		},

		{
			"PlayerName" : "Carlos Estevez",
			"Position" :  "P"
		},

		{
			"PlayerName" : "Kyle Freeland",
			"Position" :  "P"
		},

		{
			"PlayerName" : "Jon Gray",
			"Position" :  "P"
		},

		{
			"PlayerName" : "Jeff Hoffman",
			"Position" :  "P"
		},

		{
			"PlayerName" : "Greg Holland",
			"Position" :  "P"
		},

		{
			"PlayerName" : "German Marquez",
			"Position" :  "P"
		},

		{
			"PlayerName" : "Jake McGee",
			"Position" :  "P"
		},

		{
			"PlayerName" : "Pat Neshek",
			"Position" :  "P"
		},

		{
			"PlayerName" : "Scott Oberg",
			"Position" :  "P"
		},

		{
			"PlayerName" : "Adam Ottavino",
			"Position" :  "P"
		},

		{
			"PlayerName" : "Zac Rosscup",
			"Position" :  "P"
		},

		{
			"PlayerName" : "Chris Rusin",
			"Position" :  "P"
		},

		{
			"PlayerName" : "Antonio Senzatela",
			"Position" :  "P"
		},

		{
			"PlayerName" : "Ryan Hanigan",
			"Position" :  "C"
		},

		{
			"PlayerName" : "Jonathan Lucroy",
			"Position" :  "C"
		},

		{
			"PlayerName" : "Tom Murphy",
			"Position" :  "C"
		},

		{
			"PlayerName" : "Tony Wolters",
			"Position" :  "C"
		},

		{
			"PlayerName" : "Alexi Amarista",
			"Position" :  "IF"
		},

		{
			"PlayerName" : "Nolan Arenado",
			"Position" :  "IF"
		},

		{
			"PlayerName" : "DJ LeMahieu",
			"Position" :  "IF"
		},

		{
			"PlayerName" : "Ryan McMahon",
			"Position" :  "IF"
		},

		{
			"PlayerName" : "Mark Reynolds",
			"Position" :  "IF"
		},

		{
			"PlayerName" : "Trevor Story",
			"Position" :  "IF"
		},

		{
			"PlayerName" : "Pat Valaika",
			"Position" :  "IF"
		},

		{
			"PlayerName" : "Charlie Blackmon",
			"Position" :  "OF"
		},

		{
			"PlayerName" : "Ian Desmond",
			"Position" :  "OF"
		},

		{
			"PlayerName" : "Carlos Gonzalez",
			"Position" :  "OF"
		},

		{
			"PlayerName" : "Gerardo Parra",
			"Position" :  "OF"
		},

		{
			"PlayerName" : "Raimel Tapia",
			"Position" :  "OF"
		},

		{
			"PlayerName" : "Mike Tauchman",
			"Position" :  "OF"
		}
		]
	},
 	"hou": {
 		"Players" : [
		{
			"PlayerName" : "Tyler Clippard",
			"Position" :  "P"
		},

		{
			"PlayerName" : "Chris Devenski",
			"Position" :  "P"
		},

		{
			"PlayerName" : "Michael Feliz",
			"Position" :  "P"
		},

		{
			"PlayerName" : "Mike Fiers",
			"Position" :  "P"
		},

		{
			"PlayerName" : "Ken Giles",
			"Position" :  "P"
		},

		{
			"PlayerName" : "Luke Gregerson",
			"Position" :  "P"
		},

		{
			"PlayerName" : "Reymin Guduan",
			"Position" :  "P"
		},

		{
			"PlayerName" : "Will Harris",
			"Position" :  "P"
		},

		{
			"PlayerName" : "James Hoyt",
			"Position" :  "P"
		},

		{
			"PlayerName" : "Dallas Keuchel",
			"Position" :  "P"
		},

		{
			"PlayerName" : "Francisco Liriano",
			"Position" :  "P"
		},

		{
			"PlayerName" : "Francis Martes",
			"Position" :  "P"
		},

		{
			"PlayerName" : "Lance McCullers Jr.",
			"Position" :  "P"
		},

		{
			"PlayerName" : "Collin McHugh",
			"Position" :  "P"
		},

		{
			"PlayerName" : "Charlie Morton",
			"Position" :  "P"
		},

		{
			"PlayerName" : "Joe Musgrove",
			"Position" :  "P"
		},

		{
			"PlayerName" : "Brad Peacock",
			"Position" :  "P"
		},

		{
			"PlayerName" : "Tony Sipp",
			"Position" :  "P"
		},

		{
			"PlayerName" : "Justin Verlander",
			"Position" :  "P"
		},

		{
			"PlayerName" : "Juan Centeno",
			"Position" :  "C"
		},

		{
			"PlayerName" : "Evan Gattis",
			"Position" :  "C"
		},

		{
			"PlayerName" : "Brian McCann",
			"Position" :  "C"
		},

		{
			"PlayerName" : "Max Stassi",
			"Position" :  "C"
		},

		{
			"PlayerName" : "Jose Altuve",
			"Position" :  "IF"
		},

		{
			"PlayerName" : "Alex Bregman",
			"Position" :  "IF"
		},

		{
			"PlayerName" : "Carlos Correa",
			"Position" :  "IF"
		},

		{
			"PlayerName" : "J.D. Davis",
			"Position" :  "IF"
		},

		{
			"PlayerName" : "Yuli Gurriel",
			"Position" :  "IF"
		},

		{
			"PlayerName" : "Tony Kemp",
			"Position" :  "IF"
		},

		{
			"PlayerName" : "Tyler White",
			"Position" :  "IF"
		},

		{
			"PlayerName" : "Derek Fisher",
			"Position" :  "OF"
		},

		{
			"PlayerName" : "Marwin Gonzalez",
			"Position" :  "OF"
		},

		{
			"PlayerName" : "Jake Marisnick",
			"Position" :  "OF"
		},

		{
			"PlayerName" : "Cameron Maybin",
			"Position" :  "OF"
		},

		{
			"PlayerName" : "Josh Reddick",
			"Position" :  "OF"
		},

		{
			"PlayerName" : "George Springer",
			"Position" :  "OF"
		},

		{
			"PlayerName" : "Carlos Beltran",
			"Position" :  "DH"
		}
		]
	},
 	"cle": {
 		"Players" : [
		{
			"PlayerName" : "Cody Allen",
			"Position" :  "P"
		},

		{
			"PlayerName" : "Shawn Armstrong",
			"Position" :  "P"
		},

		{
			"PlayerName" : "Trevor Bauer",
			"Position" :  "P"
		},

		{
			"PlayerName" : "Craig Breslow",
			"Position" :  "P"
		},

		{
			"PlayerName" : "Carlos Carrasco",
			"Position" :  "P"
		},

		{
			"PlayerName" : "Mike Clevinger",
			"Position" :  "P"
		},

		{
			"PlayerName" : "Kyle Crockett",
			"Position" :  "P"
		},

		{
			"PlayerName" : "Nick Goody",
			"Position" :  "P"
		},

		{
			"PlayerName" : "Corey Kluber",
			"Position" :  "P"
		},

		{
			"PlayerName" : "Zach McAllister",
			"Position" :  "P"
		},

		{
			"PlayerName" : "Ryan Merritt",
			"Position" :  "P"
		},

		{
			"PlayerName" : "Shawn Morimando",
			"Position" :  "P"
		},

		{
			"PlayerName" : "Tyler Olson",
			"Position" :  "P"
		},

		{
			"PlayerName" : "Dan Otero",
			"Position" :  "P"
		},

		{
			"PlayerName" : "Danny Salazar",
			"Position" :  "P"
		},

		{
			"PlayerName" : "Bryan Shaw",
			"Position" :  "P"
		},

		{
			"PlayerName" : "Joe Smith",
			"Position" :  "P"
		},

		{
			"PlayerName" : "Josh Tomlin",
			"Position" :  "P"
		},

		{
			"PlayerName" : "Yan Gomes",
			"Position" :  "C"
		},

		{
			"PlayerName" : "Francisco Mejia",
			"Position" :  "C"
		},

		{
			"PlayerName" : "Roberto Perez",
			"Position" :  "C"
		},

		{
			"PlayerName" : "Yandy Diaz",
			"Position" :  "IF"
		},

		{
			"PlayerName" : "Erik Gonzalez",
			"Position" :  "IF"
		},

		{
			"PlayerName" : "Francisco Lindor",
			"Position" :  "IF"
		},

		{
			"PlayerName" : "Jose Ramirez",
			"Position" :  "IF"
		},

		{
			"PlayerName" : "Carlos Santana",
			"Position" :  "IF"
		},

		{
			"PlayerName" : "Giovanny Urshela",
			"Position" :  "IF"
		},

		{
			"PlayerName" : "Greg Allen",
			"Position" :  "OF"
		},

		{
			"PlayerName" : "Abraham Almonte",
			"Position" :  "OF"
		},

		{
			"PlayerName" : "Jay Bruce",
			"Position" :  "OF"
		},

		{
			"PlayerName" : "Lonnie Chisenhall",
			"Position" :  "OF"
		},

		{
			"PlayerName" : "Brandon Guyer",
			"Position" :  "OF"
		},

		{
			"PlayerName" : "Austin Jackson",
			"Position" :  "OF"
		},

		{
			"PlayerName" : "Tyler Naquin",
			"Position" :  "OF"
		},

		{
			"PlayerName" : "Bradley Zimmer",
			"Position" :  "OF"
		},

		{
			"PlayerName" : "Edwin Encarnacion",
			"Position" :  "DH"
		}
		]
	},
 	"det": {
 		"Players" : [
		{
			"PlayerName" : "Victor Alcantara",
			"Position" :  "P"
		},

		{
			"PlayerName" : "Chad Bell",
			"Position" :  "P"
		},

		{
			"PlayerName" : "Matthew Boyd",
			"Position" :  "P"
		},

		{
			"PlayerName" : "Buck Farmer",
			"Position" :  "P"
		},

		{
			"PlayerName" : "Jeff Ferrell",
			"Position" :  "P"
		},

		{
			"PlayerName" : "Michael Fulmer",
			"Position" :  "P"
		},

		{
			"PlayerName" : "Shane Greene",
			"Position" :  "P"
		},

		{
			"PlayerName" : "Blaine Hardy",
			"Position" :  "P"
		},

		{
			"PlayerName" : "Myles Jaye",
			"Position" :  "P"
		},

		{
			"PlayerName" : "Joe Jimenez",
			"Position" :  "P"
		},

		{
			"PlayerName" : "Jairo Labourt",
			"Position" :  "P"
		},

		{
			"PlayerName" : "Artie Lewicki",
			"Position" :  "P"
		},

		{
			"PlayerName" : "Daniel Norris",
			"Position" :  "P"
		},

		{
			"PlayerName" : "Zac Reininger",
			"Position" :  "P"
		},

		{
			"PlayerName" : "Anibal Sanchez",
			"Position" :  "P"
		},

		{
			"PlayerName" : "Warwick Saupold",
			"Position" :  "P"
		},

		{
			"PlayerName" : "Daniel Stumpf",
			"Position" :  "P"
		},

		{
			"PlayerName" : "Drew VerHagen",
			"Position" :  "P"
		},

		{
			"PlayerName" : "Alex Wilson",
			"Position" :  "P"
		},

		{
			"PlayerName" : "Jordan Zimmermann",
			"Position" :  "P"
		},

		{
			"PlayerName" : "Bryan Holaday",
			"Position" :  "C"
		},

		{
			"PlayerName" : "James McCann",
			"Position" :  "C"
		},

		{
			"PlayerName" : "Miguel Cabrera",
			"Position" :  "IF"
		},

		{
			"PlayerName" : "Jeimer Candelario",
			"Position" :  "IF"
		},

		{
			"PlayerName" : "Nicholas Castellanos",
			"Position" :  "IF"
		},

		{
			"PlayerName" : "John Hicks",
			"Position" :  "IF"
		},

		{
			"PlayerName" : "Jose Iglesias",
			"Position" :  "IF"
		},

		{
			"PlayerName" : "Ian Kinsler",
			"Position" :  "IF"
		},

		{
			"PlayerName" : "Dixon Machado",
			"Position" :  "IF"
		},

		{
			"PlayerName" : "Efren Navarro",
			"Position" :  "IF"
		},

		{
			"PlayerName" : "JaCoby Jones",
			"Position" :  "OF"
		},

		{
			"PlayerName" : "Mikie Mahtook",
			"Position" :  "OF"
		},

		{
			"PlayerName" : "Alex Presley",
			"Position" :  "OF"
		},

		{
			"PlayerName" : "Andrew Romine",
			"Position" :  "OF"
		}
		]
	},
 	"mia": {
 		"Players" : [
		{
			"PlayerName" : "Kyle Barraclough",
			"Position" :  "P"
		},

		{
			"PlayerName" : "Wei-Yin Chen",
			"Position" :  "P"
		},

		{
			"PlayerName" : "Adam Conley",
			"Position" :  "P"
		},

		{
			"PlayerName" : "Odrisamer Despaigne",
			"Position" :  "P"
		},

		{
			"PlayerName" : "Brian Ellington",
			"Position" :  "P"
		},

		{
			"PlayerName" : "Jarlin Garcia",
			"Position" :  "P"
		},

		{
			"PlayerName" : "Javy Guerra",
			"Position" :  "P"
		},

		{
			"PlayerName" : "Dustin McGowan",
			"Position" :  "P"
		},

		{
			"PlayerName" : "Justin Nicolino",
			"Position" :  "P"
		},

		{
			"PlayerName" : "Dillon Peters",
			"Position" :  "P"
		},

		{
			"PlayerName" : "Drew Steckenrider",
			"Position" :  "P"
		},

		{
			"PlayerName" : "Dan Straily",
			"Position" :  "P"
		},

		{
			"PlayerName" : "Junichi Tazawa",
			"Position" :  "P"
		},

		{
			"PlayerName" : "Jose Urena",
			"Position" :  "P"
		},

		{
			"PlayerName" : "Vance Worley",
			"Position" :  "P"
		},

		{
			"PlayerName" : "Brad Ziegler",
			"Position" :  "P"
		},

		{
			"PlayerName" : "A.J. Ellis",
			"Position" :  "C"
		},

		{
			"PlayerName" : "J.T. Realmuto",
			"Position" :  "C"
		},

		{
			"PlayerName" : "Brian Anderson",
			"Position" :  "IF"
		},

		{
			"PlayerName" : "Mike Aviles",
			"Position" :  "IF"
		},

		{
			"PlayerName" : "Justin Bour",
			"Position" :  "IF"
		},

		{
			"PlayerName" : "Derek Dietrich",
			"Position" :  "IF"
		},

		{
			"PlayerName" : "Dee Gordon",
			"Position" :  "IF"
		},

		{
			"PlayerName" : "Tyler Moore",
			"Position" :  "IF"
		},

		{
			"PlayerName" : "Miguel Rojas",
			"Position" :  "IF"
		},

		{
			"PlayerName" : "Tomas Telis",
			"Position" :  "IF"
		},

		{
			"PlayerName" : "Marcell Ozuna",
			"Position" :  "OF"
		},

		{
			"PlayerName" : "Giancarlo Stanton",
			"Position" :  "OF"
		},

		{
			"PlayerName" : "Ichiro Suzuki",
			"Position" :  "OF"
		},

		{
			"PlayerName" : "Christian Yelich",
			"Position" :  "OF"
		}
		]
	},
 	"phi": {
 		"Players" : [
		{
			"PlayerName" : "Luis Garcia",
			"Position" :  "P"
		},

		{
			"PlayerName" : "Mark Leiter",
			"Position" :  "P"
		},

		{
			"PlayerName" : "Ben Lively",
			"Position" :  "P"
		},

		{
			"PlayerName" : "Hoby Milner",
			"Position" :  "P"
		},

		{
			"PlayerName" : "Adam Morgan",
			"Position" :  "P"
		},

		{
			"PlayerName" : "Hector Neris",
			"Position" :  "P"
		},

		{
			"PlayerName" : "Aaron Nola",
			"Position" :  "P"
		},

		{
			"PlayerName" : "Ricardo Pinto",
			"Position" :  "P"
		},

		{
			"PlayerName" : "Nick Pivetta",
			"Position" :  "P"
		},

		{
			"PlayerName" : "Edubray Ramos",
			"Position" :  "P"
		},

		{
			"PlayerName" : "Yacksel Rios",
			"Position" :  "P"
		},

		{
			"PlayerName" : "Kevin Siegrist",
			"Position" :  "P"
		},

		{
			"PlayerName" : "Jesen Therrien",
			"Position" :  "P"
		},

		{
			"PlayerName" : "Jake Thompson",
			"Position" :  "P"
		},

		{
			"PlayerName" : "Jorge Alfaro",
			"Position" :  "C"
		},

		{
			"PlayerName" : "Cameron Rupp",
			"Position" :  "C"
		},

		{
			"PlayerName" : "Andres Blanco",
			"Position" :  "IF"
		},

		{
			"PlayerName" : "J.P. Crawford",
			"Position" :  "IF"
		},

		{
			"PlayerName" : "Maikel Franco",
			"Position" :  "IF"
		},

		{
			"PlayerName" : "Freddy Galvis",
			"Position" :  "IF"
		},

		{
			"PlayerName" : "Cesar Hernandez",
			"Position" :  "IF"
		},

		{
			"PlayerName" : "Tommy Joseph",
			"Position" :  "IF"
		},

		{
			"PlayerName" : "Ty Kelly",
			"Position" :  "IF"
		},

		{
			"PlayerName" : "Aaron Altherr",
			"Position" :  "OF"
		},

		{
			"PlayerName" : "Odubel Herrera",
			"Position" :  "OF"
		},

		{
			"PlayerName" : "Rhys Hoskins",
			"Position" :  "OF"
		},

		{
			"PlayerName" : "Hyun Soo Kim",
			"Position" :  "OF"
		},

		{
			"PlayerName" : "Daniel Nava",
			"Position" :  "OF"
		},

		{
			"PlayerName" : "Cameron Perkins",
			"Position" :  "OF"
		},

		{
			"PlayerName" : "Nick Williams",
			"Position" :  "OF"
		}
		]
	},
 	"cin": {
 		"Players" : [
		{
			"PlayerName" : "Tim Adleman",
			"Position" :  "P"
		},

		{
			"PlayerName" : "Homer Bailey",
			"Position" :  "P"
		},

		{
			"PlayerName" : "Luis Castillo",
			"Position" :  "P"
		},

		{
			"PlayerName" : "Alejandro Chacin",
			"Position" :  "P"
		},

		{
			"PlayerName" : "Rookie Davis",
			"Position" :  "P"
		},

		{
			"PlayerName" : "Luke Farrell",
			"Position" :  "P"
		},

		{
			"PlayerName" : "Amir Garrett",
			"Position" :  "P"
		},

		{
			"PlayerName" : "Ariel Hernandez",
			"Position" :  "P"
		},

		{
			"PlayerName" : "Raisel Iglesias",
			"Position" :  "P"
		},

		{
			"PlayerName" : "Michael Lorenzen",
			"Position" :  "P"
		},

		{
			"PlayerName" : "Tyler Mahle",
			"Position" :  "P"
		},

		{
			"PlayerName" : "Wandy Peralta",
			"Position" :  "P"
		},

		{
			"PlayerName" : "Cody Reed",
			"Position" :  "P"
		},

		{
			"PlayerName" : "Sal Romano",
			"Position" :  "P"
		},

		{
			"PlayerName" : "Kevin Shackelford",
			"Position" :  "P"
		},

		{
			"PlayerName" : "Jackson Stephens",
			"Position" :  "P"
		},

		{
			"PlayerName" : "Robert Stephenson",
			"Position" :  "P"
		},

		{
			"PlayerName" : "Drew Storen",
			"Position" :  "P"
		},

		{
			"PlayerName" : "Asher Wojciechowski",
			"Position" :  "P"
		},

		{
			"PlayerName" : "Tucker Barnhart",
			"Position" :  "C"
		},

		{
			"PlayerName" : "Stuart Turner",
			"Position" :  "C"
		},

		{
			"PlayerName" : "Chad Wallach",
			"Position" :  "C"
		},

		{
			"PlayerName" : "Zack Cozart",
			"Position" :  "IF"
		},

		{
			"PlayerName" : "Scooter Gennett",
			"Position" :  "IF"
		},

		{
			"PlayerName" : "Jose Peraza",
			"Position" :  "IF"
		},

		{
			"PlayerName" : "Eugenio Suarez",
			"Position" :  "IF"
		},

		{
			"PlayerName" : "Zach Vincej",
			"Position" :  "IF"
		},

		{
			"PlayerName" : "Joey Votto",
			"Position" :  "IF"
		},

		{
			"PlayerName" : "Adam Duvall",
			"Position" :  "OF"
		},

		{
			"PlayerName" : "Phillip Ervin",
			"Position" :  "OF"
		},

		{
			"PlayerName" : "Patrick Kivlehan",
			"Position" :  "OF"
		},

		{
			"PlayerName" : "Scott Schebler",
			"Position" :  "OF"
		}
		]
	},
 	"atl": {
 		"Players" : [
		{
			"PlayerName" : "Rex Brothers",
			"Position" :  "P"
		},

		{
			"PlayerName" : "R.A. Dickey",
			"Position" :  "P"
		},

		{
			"PlayerName" : "Mike Foltynewicz",
			"Position" :  "P"
		},

		{
			"PlayerName" : "Sam Freeman",
			"Position" :  "P"
		},

		{
			"PlayerName" : "Max Fried",
			"Position" :  "P"
		},

		{
			"PlayerName" : "Luiz Gohara",
			"Position" :  "P"
		},

		{
			"PlayerName" : "Luke Jackson",
			"Position" :  "P"
		},

		{
			"PlayerName" : "Jim Johnson",
			"Position" :  "P"
		},

		{
			"PlayerName" : "Ian Krol",
			"Position" :  "P"
		},

		{
			"PlayerName" : "A.J. Minter",
			"Position" :  "P"
		},

		{
			"PlayerName" : "Sean Newcomb",
			"Position" :  "P"
		},

		{
			"PlayerName" : "Jose Ramirez",
			"Position" :  "P"
		},

		{
			"PlayerName" : "Lucas Sims",
			"Position" :  "P"
		},

		{
			"PlayerName" : "Julio Teheran",
			"Position" :  "P"
		},

		{
			"PlayerName" : "Arodys Vizcaino",
			"Position" :  "P"
		},

		{
			"PlayerName" : "Dan Winkler",
			"Position" :  "P"
		},

		{
			"PlayerName" : "Matt Wisler",
			"Position" :  "P"
		},

		{
			"PlayerName" : "Tyler Flowers",
			"Position" :  "C"
		},

		{
			"PlayerName" : "David Freitas",
			"Position" :  "C"
		},

		{
			"PlayerName" : "Tony Sanchez",
			"Position" :  "C"
		},

		{
			"PlayerName" : "Kurt Suzuki",
			"Position" :  "C"
		},

		{
			"PlayerName" : "Matt Adams",
			"Position" :  "IF"
		},

		{
			"PlayerName" : "Ozzie Albies",
			"Position" :  "IF"
		},

		{
			"PlayerName" : "Johan Camargo",
			"Position" :  "IF"
		},

		{
			"PlayerName" : "Freddie Freeman",
			"Position" :  "IF"
		},

		{
			"PlayerName" : "Adonis Garcia",
			"Position" :  "IF"
		},

		{
			"PlayerName" : "Jace Peterson",
			"Position" :  "IF"
		},

		{
			"PlayerName" : "Rio Ruiz",
			"Position" :  "IF"
		},

		{
			"PlayerName" : "Dansby Swanson",
			"Position" :  "IF"
		},

		{
			"PlayerName" : "Lane Adams",
			"Position" :  "OF"
		},

		{
			"PlayerName" : "Ender Inciarte",
			"Position" :  "OF"
		},

		{
			"PlayerName" : "Micah Johnson",
			"Position" :  "OF"
		},

		{
			"PlayerName" : "Matt Kemp",
			"Position" :  "OF"
		},

		{
			"PlayerName" : "Nick Markakis",
			"Position" :  "OF"
		}
		]
	},
 	"chc": {
 		"Players" : [
		{
			"PlayerName" : "Jake Arrieta",
			"Position" :  "P"
		},

		{
			"PlayerName" : "Wade Davis",
			"Position" :  "P"
		},

		{
			"PlayerName" : "Brian Duensing",
			"Position" :  "P"
		},

		{
			"PlayerName" : "Carl Edwards Jr.",
			"Position" :  "P"
		},

		{
			"PlayerName" : "Justin Grimm",
			"Position" :  "P"
		},

		{
			"PlayerName" : "Kyle Hendricks",
			"Position" :  "P"
		},

		{
			"PlayerName" : "John Lackey",
			"Position" :  "P"
		},

		{
			"PlayerName" : "Jon Lester",
			"Position" :  "P"
		},

		{
			"PlayerName" : "Dillon Maples",
			"Position" :  "P"
		},

		{
			"PlayerName" : "Mike Montgomery",
			"Position" :  "P"
		},

		{
			"PlayerName" : "Felix Pena",
			"Position" :  "P"
		},

		{
			"PlayerName" : "Jose Quintana",
			"Position" :  "P"
		},

		{
			"PlayerName" : "Hector Rondon",
			"Position" :  "P"
		},

		{
			"PlayerName" : "Pedro Strop",
			"Position" :  "P"
		},

		{
			"PlayerName" : "Koji Uehara",
			"Position" :  "P"
		},

		{
			"PlayerName" : "Justin Wilson",
			"Position" :  "P"
		},

		{
			"PlayerName" : "Rob Zastryzny",
			"Position" :  "P"
		},

		{
			"PlayerName" : "Alex Avila",
			"Position" :  "C"
		},

		{
			"PlayerName" : "Victor Caratini",
			"Position" :  "C"
		},

		{
			"PlayerName" : "Willson Contreras",
			"Position" :  "C"
		},

		{
			"PlayerName" : "Taylor Davis",
			"Position" :  "C"
		},

		{
			"PlayerName" : "Rene Rivera",
			"Position" :  "C"
		},

		{
			"PlayerName" : "Javier Baez",
			"Position" :  "IF"
		},

		{
			"PlayerName" : "Kris Bryant",
			"Position" :  "IF"
		},

		{
			"PlayerName" : "Mike Freeman",
			"Position" :  "IF"
		},

		{
			"PlayerName" : "Tommy La Stella",
			"Position" :  "IF"
		},

		{
			"PlayerName" : "Anthony Rizzo",
			"Position" :  "IF"
		},

		{
			"PlayerName" : "Ben Zobrist",
			"Position" :  "IF"
		},

		{
			"PlayerName" : "Albert Almora Jr.",
			"Position" :  "OF"
		},

		{
			"PlayerName" : "Ian Happ",
			"Position" :  "OF"
		},

		{
			"PlayerName" : "Jason Heyward",
			"Position" :  "OF"
		},

		{
			"PlayerName" : "Jon Jay",
			"Position" :  "OF"
		},

		{
			"PlayerName" : "Leonys Martin",
			"Position" :  "OF"
		},

		{
			"PlayerName" : "Kyle Schwarber",
			"Position" :  "OF"
		}
		]
	},
 	"cws": {
 		"Players" : [
		{
			"PlayerName" : "Al Alburquerque",
			"Position" :  "P"
		},

		{
			"PlayerName" : "Chris Beck",
			"Position" :  "P"
		},

		{
			"PlayerName" : "Aaron Bummer",
			"Position" :  "P"
		},

		{
			"PlayerName" : "Dylan Covey",
			"Position" :  "P"
		},

		{
			"PlayerName" : "Danny Farquhar",
			"Position" :  "P"
		},

		{
			"PlayerName" : "Jace Fry",
			"Position" :  "P"
		},

		{
			"PlayerName" : "Carson Fulmer",
			"Position" :  "P"
		},

		{
			"PlayerName" : "Lucas Giolito",
			"Position" :  "P"
		},

		{
			"PlayerName" : "David Holmberg",
			"Position" :  "P"
		},

		{
			"PlayerName" : "Gregory Infante",
			"Position" :  "P"
		},

		{
			"PlayerName" : "Reynaldo Lopez",
			"Position" :  "P"
		},

		{
			"PlayerName" : "Juan Minaya",
			"Position" :  "P"
		},

		{
			"PlayerName" : "Mike Pelfrey",
			"Position" :  "P"
		},

		{
			"PlayerName" : "James Shields",
			"Position" :  "P"
		},

		{
			"PlayerName" : "Chris Volstad",
			"Position" :  "P"
		},

		{
			"PlayerName" : "Rob Brantly",
			"Position" :  "C"
		},

		{
			"PlayerName" : "Omar Narvaez",
			"Position" :  "C"
		},

		{
			"PlayerName" : "Kevan Smith",
			"Position" :  "C"
		},

		{
			"PlayerName" : "Jose Abreu",
			"Position" :  "IF"
		},

		{
			"PlayerName" : "Tim Anderson",
			"Position" :  "IF"
		},

		{
			"PlayerName" : "Yoan Moncada",
			"Position" :  "IF"
		},

		{
			"PlayerName" : "Tyler Saladino",
			"Position" :  "IF"
		},

		{
			"PlayerName" : "Yolmer Sanchez",
			"Position" :  "IF"
		},

		{
			"PlayerName" : "Adam Engel",
			"Position" :  "OF"
		},

		{
			"PlayerName" : "Avisail Garcia",
			"Position" :  "OF"
		},

		{
			"PlayerName" : "Alen Hanson",
			"Position" :  "OF"
		},

		{
			"PlayerName" : "Rymer Liriano",
			"Position" :  "OF"
		},

		{
			"PlayerName" : "Matt Davidson",
			"Position" :  "DH"
		},

		{
			"PlayerName" : "Nicky Delmonico",
			"Position" :  "DH"
		}
		]
	},
 	"wsh": {
 		"Players" : [
		{
			"PlayerName" : "Austin Adams",
			"Position" :  "P"
		},

		{
			"PlayerName" : "Matt Albers",
			"Position" :  "P"
		},

		{
			"PlayerName" : "Joe Blanton",
			"Position" :  "P"
		},

		{
			"PlayerName" : "A.J. Cole",
			"Position" :  "P"
		},

		{
			"PlayerName" : "Sean Doolittle",
			"Position" :  "P"
		},

		{
			"PlayerName" : "Gio Gonzalez",
			"Position" :  "P"
		},

		{
			"PlayerName" : "Matt Grace",
			"Position" :  "P"
		},

		{
			"PlayerName" : "Edwin Jackson",
			"Position" :  "P"
		},

		{
			"PlayerName" : "Shawn Kelley",
			"Position" :  "P"
		},

		{
			"PlayerName" : "Brandon Kintzler",
			"Position" :  "P"
		},

		{
			"PlayerName" : "Ryan Madson",
			"Position" :  "P"
		},

		{
			"PlayerName" : "Oliver Perez",
			"Position" :  "P"
		},

		{
			"PlayerName" : "Tanner Roark",
			"Position" :  "P"
		},

		{
			"PlayerName" : "Enny Romero",
			"Position" :  "P"
		},

		{
			"PlayerName" : "Max Scherzer",
			"Position" :  "P"
		},

		{
			"PlayerName" : "Sammy Solis",
			"Position" :  "P"
		},

		{
			"PlayerName" : "Stephen Strasburg",
			"Position" :  "P"
		},

		{
			"PlayerName" : "Jose Lobaton",
			"Position" :  "C"
		},

		{
			"PlayerName" : "Raudy Read",
			"Position" :  "C"
		},

		{
			"PlayerName" : "Pedro Severino",
			"Position" :  "C"
		},

		{
			"PlayerName" : "Matt Wieters",
			"Position" :  "C"
		},

		{
			"PlayerName" : "Wilmer Difo",
			"Position" :  "IF"
		},

		{
			"PlayerName" : "Adam Lind",
			"Position" :  "IF"
		},

		{
			"PlayerName" : "Daniel Murphy",
			"Position" :  "IF"
		},

		{
			"PlayerName" : "Anthony Rendon",
			"Position" :  "IF"
		},

		{
			"PlayerName" : "Adrian Sanchez",
			"Position" :  "IF"
		},

		{
			"PlayerName" : "Trea Turner",
			"Position" :  "IF"
		},

		{
			"PlayerName" : "Ryan Zimmerman",
			"Position" :  "IF"
		},

		{
			"PlayerName" : "Rafael Bautista",
			"Position" :  "OF"
		},

		{
			"PlayerName" : "Alejandro De Aza",
			"Position" :  "OF"
		},

		{
			"PlayerName" : "Howie Kendrick",
			"Position" :  "OF"
		},

		{
			"PlayerName" : "Victor Robles",
			"Position" :  "OF"
		},

		{
			"PlayerName" : "Andrew Stevenson",
			"Position" :  "OF"
		},

		{
			"PlayerName" : "Michael A. Taylor",
			"Position" :  "OF"
		},

		{
			"PlayerName" : "Jayson Werth",
			"Position" :  "OF"
		}
		]
	},
 	"mil": {
 		"Players" : [
		{
			"PlayerName" : "Chase Anderson",
			"Position" :  "P"
		},

		{
			"PlayerName" : "Jacob Barnes",
			"Position" :  "P"
		},

		{
			"PlayerName" : "Zach Davies",
			"Position" :  "P"
		},

		{
			"PlayerName" : "Oliver Drake",
			"Position" :  "P"
		},

		{
			"PlayerName" : "Matt Garza",
			"Position" :  "P"
		},

		{
			"PlayerName" : "Junior Guerra",
			"Position" :  "P"
		},

		{
			"PlayerName" : "Josh Hader",
			"Position" :  "P"
		},

		{
			"PlayerName" : "Jared Hughes",
			"Position" :  "P"
		},

		{
			"PlayerName" : "Jeremy Jeffress",
			"Position" :  "P"
		},

		{
			"PlayerName" : "Corey Knebel",
			"Position" :  "P"
		},

		{
			"PlayerName" : "Jimmy Nelson",
			"Position" :  "P"
		},

		{
			"PlayerName" : "Brent Suter",
			"Position" :  "P"
		},

		{
			"PlayerName" : "Anthony Swarzak",
			"Position" :  "P"
		},

		{
			"PlayerName" : "Carlos Torres",
			"Position" :  "P"
		},

		{
			"PlayerName" : "Wei-Chung Wang",
			"Position" :  "P"
		},

		{
			"PlayerName" : "Taylor Williams",
			"Position" :  "P"
		},

		{
			"PlayerName" : "Brandon Woodruff",
			"Position" :  "P"
		},

		{
			"PlayerName" : "Jett Bandy",
			"Position" :  "C"
		},

		{
			"PlayerName" : "Manny Pina",
			"Position" :  "C"
		},

		{
			"PlayerName" : "Andrew Susac",
			"Position" :  "C"
		},

		{
			"PlayerName" : "Stephen Vogt",
			"Position" :  "C"
		},

		{
			"PlayerName" : "Jesus Aguilar",
			"Position" :  "IF"
		},

		{
			"PlayerName" : "Orlando Arcia",
			"Position" :  "IF"
		},

		{
			"PlayerName" : "Travis Shaw",
			"Position" :  "IF"
		},

		{
			"PlayerName" : "Eric Sogard",
			"Position" :  "IF"
		},

		{
			"PlayerName" : "Eric Thames",
			"Position" :  "IF"
		},

		{
			"PlayerName" : "Jonathan Villar",
			"Position" :  "IF"
		},

		{
			"PlayerName" : "Neil Walker",
			"Position" :  "IF"
		},

		{
			"PlayerName" : "Quintin Berry",
			"Position" :  "OF"
		},

		{
			"PlayerName" : "Ryan Braun",
			"Position" :  "OF"
		},

		{
			"PlayerName" : "Keon Broxton",
			"Position" :  "OF"
		},

		{
			"PlayerName" : "Hernan Perez",
			"Position" :  "OF"
		},

		{
			"PlayerName" : "Brett Phillips",
			"Position" :  "OF"
		},

		{
			"PlayerName" : "Domingo Santana",
			"Position" :  "OF"
		}
		]
	},
 	"ari": {
 		"Players" : [
		{
			"PlayerName" : "Anthony Banda",
			"Position" :  "P"
		},

		{
			"PlayerName" : "Jake Barrett",
			"Position" :  "P"
		},

		{
			"PlayerName" : "Silvino Bracho",
			"Position" :  "P"
		},

		{
			"PlayerName" : "Archie Bradley",
			"Position" :  "P"
		},

		{
			"PlayerName" : "Andrew Chafin",
			"Position" :  "P"
		},

		{
			"PlayerName" : "Patrick Corbin",
			"Position" :  "P"
		},

		{
			"PlayerName" : "Jorge De La Rosa",
			"Position" :  "P"
		},

		{
			"PlayerName" : "Zack Godley",
			"Position" :  "P"
		},

		{
			"PlayerName" : "Zack Greinke",
			"Position" :  "P"
		},

		{
			"PlayerName" : "David Hernandez",
			"Position" :  "P"
		},

		{
			"PlayerName" : "J.J. Hoover",
			"Position" :  "P"
		},

		{
			"PlayerName" : "T.J. McFarland",
			"Position" :  "P"
		},

		{
			"PlayerName" : "Robbie Ray",
			"Position" :  "P"
		},

		{
			"PlayerName" : "Fernando Rodney",
			"Position" :  "P"
		},

		{
			"PlayerName" : "Jimmie Sherfy",
			"Position" :  "P"
		},

		{
			"PlayerName" : "Braden Shipley",
			"Position" :  "P"
		},

		{
			"PlayerName" : "Taijuan Walker",
			"Position" :  "P"
		},

		{
			"PlayerName" : "Chris Herrmann",
			"Position" :  "C"
		},

		{
			"PlayerName" : "Chris Iannetta",
			"Position" :  "C"
		},

		{
			"PlayerName" : "John Ryan Murphy",
			"Position" :  "C"
		},

		{
			"PlayerName" : "Brandon Drury",
			"Position" :  "IF"
		},

		{
			"PlayerName" : "Paul Goldschmidt",
			"Position" :  "IF"
		},

		{
			"PlayerName" : "Jake Lamb",
			"Position" :  "IF"
		},

		{
			"PlayerName" : "Ketel Marte",
			"Position" :  "IF"
		},

		{
			"PlayerName" : "Adam Rosales",
			"Position" :  "IF"
		},

		{
			"PlayerName" : "Ildemaro Vargas",
			"Position" :  "IF"
		},

		{
			"PlayerName" : "Christian Walker",
			"Position" :  "IF"
		},

		{
			"PlayerName" : "Gregor Blanco",
			"Position" :  "OF"
		},

		{
			"PlayerName" : "Daniel Descalso",
			"Position" :  "OF"
		},

		{
			"PlayerName" : "Rey Fuentes",
			"Position" :  "OF"
		},

		{
			"PlayerName" : "Jeremy Hazelbaker",
			"Position" :  "OF"
		},

		{
			"PlayerName" : "J.D. Martinez",
			"Position" :  "OF"
		},

		{
			"PlayerName" : "Kristopher Negron",
			"Position" :  "OF"
		},

		{
			"PlayerName" : "David Peralta",
			"Position" :  "OF"
		},

		{
			"PlayerName" : "A.J. Pollock",
			"Position" :  "OF"
		}
		]
	},
 	"tex": {
 		"Players" : [
		{
			"PlayerName" : "Tony Barnette",
			"Position" :  "P"
		},

		{
			"PlayerName" : "Austin Bibens-Dirkx",
			"Position" :  "P"
		},

		{
			"PlayerName" : "Matt Bush",
			"Position" :  "P"
		},

		{
			"PlayerName" : "Andrew Cashner",
			"Position" :  "P"
		},

		{
			"PlayerName" : "Alex Claudio",
			"Position" :  "P"
		},

		{
			"PlayerName" : "Jake Diekman",
			"Position" :  "P"
		},

		{
			"PlayerName" : "Paolo Espino",
			"Position" :  "P"
		},

		{
			"PlayerName" : "Nick Gardewine",
			"Position" :  "P"
		},

		{
			"PlayerName" : "Miguel Gonzalez",
			"Position" :  "P"
		},

		{
			"PlayerName" : "A.J. Griffin",
			"Position" :  "P"
		},

		{
			"PlayerName" : "Jason Grilli",
			"Position" :  "P"
		},

		{
			"PlayerName" : "Cole Hamels",
			"Position" :  "P"
		},

		{
			"PlayerName" : "Jose Leclerc",
			"Position" :  "P"
		},

		{
			"PlayerName" : "Nick Martinez",
			"Position" :  "P"
		},

		{
			"PlayerName" : "Yohander Mendez",
			"Position" :  "P"
		},

		{
			"PlayerName" : "Martin Perez",
			"Position" :  "P"
		},

		{
			"PlayerName" : "Ricardo Rodriguez",
			"Position" :  "P"
		},

		{
			"PlayerName" : "Tyson Ross",
			"Position" :  "P"
		},

		{
			"PlayerName" : "Robinson Chirinos",
			"Position" :  "C"
		},

		{
			"PlayerName" : "A.J. Jimenez",
			"Position" :  "C"
		},

		{
			"PlayerName" : "Brett Nicholas",
			"Position" :  "C"
		},

		{
			"PlayerName" : "Elvis Andrus",
			"Position" :  "IF"
		},

		{
			"PlayerName" : "Joey Gallo",
			"Position" :  "IF"
		},

		{
			"PlayerName" : "Phil Gosselin",
			"Position" :  "IF"
		},

		{
			"PlayerName" : "Will Middlebrooks",
			"Position" :  "IF"
		},

		{
			"PlayerName" : "Mike Napoli",
			"Position" :  "IF"
		},

		{
			"PlayerName" : "Rougned Odor",
			"Position" :  "IF"
		},

		{
			"PlayerName" : "Shin-Soo Choo",
			"Position" :  "OF"
		},

		{
			"PlayerName" : "Delino DeShields",
			"Position" :  "OF"
		},

		{
			"PlayerName" : "Carlos Gomez",
			"Position" :  "OF"
		},

		{
			"PlayerName" : "Jared Hoying",
			"Position" :  "OF"
		},

		{
			"PlayerName" : "Nomar Mazara",
			"Position" :  "OF"
		},

		{
			"PlayerName" : "Drew Robinson",
			"Position" :  "OF"
		},

		{
			"PlayerName" : "Ryan Rua",
			"Position" :  "OF"
		}
		]
	},
 	"pit": {
 		"Players" : [
		{
			"PlayerName" : "Johnny Barbato",
			"Position" :  "P"
		},

		{
			"PlayerName" : "Joaquin Benoit",
			"Position" :  "P"
		},

		{
			"PlayerName" : "Steven Brault",
			"Position" :  "P"
		},

		{
			"PlayerName" : "Gerrit Cole",
			"Position" :  "P"
		},

		{
			"PlayerName" : "Tyler Glasnow",
			"Position" :  "P"
		},

		{
			"PlayerName" : "Daniel Hudson",
			"Position" :  "P"
		},

		{
			"PlayerName" : "George Kontos",
			"Position" :  "P"
		},

		{
			"PlayerName" : "Chad Kuhl",
			"Position" :  "P"
		},

		{
			"PlayerName" : "Jack Leathersich",
			"Position" :  "P"
		},

		{
			"PlayerName" : "Wade LeBlanc",
			"Position" :  "P"
		},

		{
			"PlayerName" : "Dovydas Neverauskas",
			"Position" :  "P"
		},

		{
			"PlayerName" : "Ivan Nova",
			"Position" :  "P"
		},

		{
			"PlayerName" : "Felipe Rivero",
			"Position" :  "P"
		},

		{
			"PlayerName" : "Dan Runzler",
			"Position" :  "P"
		},

		{
			"PlayerName" : "Angel Sanchez",
			"Position" :  "P"
		},

		{
			"PlayerName" : "Edgar Santana",
			"Position" :  "P"
		},

		{
			"PlayerName" : "A.J. Schugel",
			"Position" :  "P"
		},

		{
			"PlayerName" : "Jameson Taillon",
			"Position" :  "P"
		},

		{
			"PlayerName" : "Trevor Williams",
			"Position" :  "P"
		},

		{
			"PlayerName" : "Elias Diaz",
			"Position" :  "C"
		},

		{
			"PlayerName" : "Jacob Stallings",
			"Position" :  "C"
		},

		{
			"PlayerName" : "Chris Stewart",
			"Position" :  "C"
		},

		{
			"PlayerName" : "Josh Bell",
			"Position" :  "IF"
		},

		{
			"PlayerName" : "David Freese",
			"Position" :  "IF"
		},

		{
			"PlayerName" : "Jordy Mercer",
			"Position" :  "IF"
		},

		{
			"PlayerName" : "Max Moroff",
			"Position" :  "IF"
		},

		{
			"PlayerName" : "Christopher Bostick",
			"Position" :  "OF"
		},

		{
			"PlayerName" : "Adam Frazier",
			"Position" :  "OF"
		},

		{
			"PlayerName" : "John Jaso",
			"Position" :  "OF"
		},

		{
			"PlayerName" : "Jordan Luplow",
			"Position" :  "OF"
		},

		{
			"PlayerName" : "Starling Marte",
			"Position" :  "OF"
		},

		{
			"PlayerName" : "Andrew McCutchen",
			"Position" :  "OF"
		},

		{
			"PlayerName" : "Jose Osuna",
			"Position" :  "OF"
		},

		{
			"PlayerName" : "Gregory Polanco",
			"Position" :  "OF"
		},

		{
			"PlayerName" : "Sean Rodriguez",
			"Position" :  "OF"
		}
		]
	},
 	"oak": {
 		"Players" : [
		{
			"PlayerName" : "Raul Alcantara",
			"Position" :  "P"
		},

		{
			"PlayerName" : "Michael Brady",
			"Position" :  "P"
		},

		{
			"PlayerName" : "Santiago Casilla",
			"Position" :  "P"
		},

		{
			"PlayerName" : "Simon Castro",
			"Position" :  "P"
		},

		{
			"PlayerName" : "Jharel Cotton",
			"Position" :  "P"
		},

		{
			"PlayerName" : "Daniel Coulombe",
			"Position" :  "P"
		},

		{
			"PlayerName" : "Ryan Dull",
			"Position" :  "P"
		},

		{
			"PlayerName" : "Daniel Gossett",
			"Position" :  "P"
		},

		{
			"PlayerName" : "Kendall Graveman",
			"Position" :  "P"
		},

		{
			"PlayerName" : "Chris Hatcher",
			"Position" :  "P"
		},

		{
			"PlayerName" : "Liam Hendriks",
			"Position" :  "P"
		},

		{
			"PlayerName" : "Sean Manaea",
			"Position" :  "P"
		},

		{
			"PlayerName" : "Daniel Mengden",
			"Position" :  "P"
		},

		{
			"PlayerName" : "Sam Moll",
			"Position" :  "P"
		},

		{
			"PlayerName" : "Chris Smith",
			"Position" :  "P"
		},

		{
			"PlayerName" : "Blake Treinen",
			"Position" :  "P"
		},

		{
			"PlayerName" : "Dustin Garneau",
			"Position" :  "C"
		},

		{
			"PlayerName" : "Bruce Maxwell",
			"Position" :  "C"
		},

		{
			"PlayerName" : "Josh Phegley",
			"Position" :  "C"
		},

		{
			"PlayerName" : "Franklin Barreto",
			"Position" :  "IF"
		},

		{
			"PlayerName" : "Matt Chapman",
			"Position" :  "IF"
		},

		{
			"PlayerName" : "Jed Lowrie",
			"Position" :  "IF"
		},

		{
			"PlayerName" : "Matt Olson",
			"Position" :  "IF"
		},

		{
			"PlayerName" : "Chad Pinder",
			"Position" :  "IF"
		},

		{
			"PlayerName" : "Marcus Semien",
			"Position" :  "IF"
		},

		{
			"PlayerName" : "Joey Wendle",
			"Position" :  "IF"
		},

		{
			"PlayerName" : "Mark Canha",
			"Position" :  "OF"
		},

		{
			"PlayerName" : "Khris Davis",
			"Position" :  "OF"
		},

		{
			"PlayerName" : "Matt Joyce",
			"Position" :  "OF"
		},

		{
			"PlayerName" : "Renato Nunez",
			"Position" :  "OF"
		},

		{
			"PlayerName" : "Boog Powell",
			"Position" :  "OF"
		},

		{
			"PlayerName" : "Jake Smolinski",
			"Position" :  "OF"
		},

		{
			"PlayerName" : "Ryon Healy",
			"Position" :  "DH"
		}
		]
	},
 	"sea": {
 		"Players" : [
		{
			"PlayerName" : "Andrew Albers",
			"Position" :  "P"
		},

		{
			"PlayerName" : "Dan Altavilla",
			"Position" :  "P"
		},

		{
			"PlayerName" : "Edwin Diaz",
			"Position" :  "P"
		},

		{
			"PlayerName" : "Yovani Gallardo",
			"Position" :  "P"
		},

		{
			"PlayerName" : "Ryan Garton",
			"Position" :  "P"
		},

		{
			"PlayerName" : "Marco Gonzales",
			"Position" :  "P"
		},

		{
			"PlayerName" : "Casey Lawrence",
			"Position" :  "P"
		},

		{
			"PlayerName" : "Mike Leake",
			"Position" :  "P"
		},

		{
			"PlayerName" : "Ariel Miranda",
			"Position" :  "P"
		},

		{
			"PlayerName" : "Andrew Moore",
			"Position" :  "P"
		},

		{
			"PlayerName" : "Emilio Pagan",
			"Position" :  "P"
		},

		{
			"PlayerName" : "James Pazos",
			"Position" :  "P"
		},

		{
			"PlayerName" : "Erasmo Ramirez",
			"Position" :  "P"
		},

		{
			"PlayerName" : "Marc Rzepczynski",
			"Position" :  "P"
		},

		{
			"PlayerName" : "Shae Simmons",
			"Position" :  "P"
		},

		{
			"PlayerName" : "Nick Vincent",
			"Position" :  "P"
		},

		{
			"PlayerName" : "Mike Marjama",
			"Position" :  "C"
		},

		{
			"PlayerName" : "Carlos Ruiz",
			"Position" :  "C"
		},

		{
			"PlayerName" : "Mike Zunino",
			"Position" :  "C"
		},

		{
			"PlayerName" : "Yonder Alonso",
			"Position" :  "IF"
		},

		{
			"PlayerName" : "Gordon Beckham",
			"Position" :  "IF"
		},

		{
			"PlayerName" : "Robinson Cano",
			"Position" :  "IF"
		},

		{
			"PlayerName" : "Taylor Motter",
			"Position" :  "IF"
		},

		{
			"PlayerName" : "Kyle Seager",
			"Position" :  "IF"
		},

		{
			"PlayerName" : "Jean Segura",
			"Position" :  "IF"
		},

		{
			"PlayerName" : "Danny Valencia",
			"Position" :  "IF"
		},

		{
			"PlayerName" : "Daniel Vogelbach",
			"Position" :  "IF"
		},

		{
			"PlayerName" : "Jarrod Dyson",
			"Position" :  "OF"
		},

		{
			"PlayerName" : "Ben Gamel",
			"Position" :  "OF"
		},

		{
			"PlayerName" : "Mitch Haniger",
			"Position" :  "OF"
		},

		{
			"PlayerName" : "Jacob Hannemann",
			"Position" :  "OF"
		},

		{
			"PlayerName" : "Guillermo Heredia",
			"Position" :  "OF"
		},

		{
			"PlayerName" : "Nelson Cruz",
			"Position" :  "DH"
		}
		]
	}
}